pymeta/__init__.py
pymeta/boot.py
pymeta/builder.py
pymeta/grammar.py
pymeta/runtime.py
PyMeta3_wheel-0.5.1.dist-info/LICENSE
PyMeta3_wheel-0.5.1.dist-info/METADATA
PyMeta3_wheel-0.5.1.dist-info/WHEEL
PyMeta3_wheel-0.5.1.dist-info/top_level.txt
PyMeta3_wheel-0.5.1.dist-info/RECORD
