Metadata-Version: 2.1
Name: PyMeta3-wheel
Version: 0.5.1
Summary: Pattern-matching language based on OMeta for Python 3 and 2
Home-page: https://github.com/wbond/pymeta3
Author: wbond
Author-email: will@wbond.net
License: MIT License
Classifier: Development Status :: 4 - Beta
Classifier: Intended Audience :: Developers
Classifier: License :: OSI Approved :: MIT License
Classifier: Operating System :: OS Independent
Classifier: Programming Language :: Python :: 2
Classifier: Programming Language :: Python :: 2.7
Classifier: Programming Language :: Python :: 3
Classifier: Programming Language :: Python :: 3.3
Classifier: Programming Language :: Python :: 3.4
License-File: LICENSE
